{
  "id": "BUG-015",
  "title": "Add cleanup for setInterval/setTimeout in React components",
  "status": "open",
  "priority": "P2",
  "milestone": "M2",
  "tags": ["react", "memory-leak", "cleanup"],
  "summary": "Multiple React components use setInterval/setTimeout without proper cleanup, potentially causing memory leaks.",
  "acceptance": [
    "Audit all setInterval/setTimeout usage in React components",
    "Add useEffect cleanup for all timers",
    "Add ESLint rule to enforce cleanup pattern",
    "Test component unmount scenarios"
  ],
  "effort": "4 hours",
  "impact": "Medium - prevents memory leaks",
  "references": [
    "packages/admin-ui/src/components/SharedChatPanel.tsx",
    "packages/admin-ui/src/components/EnergyPanel.tsx"
  ],
  "notes": "Common React pattern mistake. Need to return cleanup function from useEffect."
}
